station/__init__.py
station/data_manager.py
station/data/__init__.py
station/data/datafile.py
station/data/gpsfile.py
station/data/nodehealthfile.py
station/data/nodelocationfile.py
station/data/rawbeepfile.py
station/locate/__init__.py
station/locate/api.py
station/locate/dataset.py
station/locate/nodedataset.py
station/locate/visualize.py
station_tools-0.1.3.dist-info/METADATA
station_tools-0.1.3.dist-info/WHEEL
station_tools-0.1.3.dist-info/top_level.txt
station_tools-0.1.3.dist-info/RECORD
