Metadata-Version: 2.1
Name: station-tools
Version: 0.1.3
Summary: A package for managing and analyzing CTT LifeTag datasets
Home-page: https://github.com/bobfogg/sensor-station-tools
Author: Bob Fogg
Author-email: bob.fogg@celltracktech.com
License: UNKNOWN
Platform: UNKNOWN
Classifier: Programming Language :: Python :: 3
Classifier: License :: OSI Approved :: MIT License
Classifier: Operating System :: OS Independent
Requires-Python: >=3.6
